AUTHORS.rst
CONTRIBUTING.rst
HISTORY.rst
LICENSE
MANIFEST.in
README.rst
setup.cfg
setup.py
docs/Makefile
docs/authors.rst
docs/conf.py
docs/contributing.rst
docs/history.rst
docs/index.rst
docs/installation.rst
docs/make.bat
docs/readme.rst
docs/usage.rst
nurgle/__init__.py
nurgle/nurgle.py
nurgle.egg-info/PKG-INFO
nurgle.egg-info/SOURCES.txt
nurgle.egg-info/dependency_links.txt
nurgle.egg-info/not-zip-safe
nurgle.egg-info/requires.txt
nurgle.egg-info/top_level.txt
tests/__init__.py
tests/test_nurgle.py