Metadata-Version: 1.2
Name: nurgle
Version: 0.1.2
Summary: Decorator based error handling for Python, with light Slack coating
Home-page: https://gitlab.com/Herout/nurgle
Author: Jan Herout
Author-email: jan.herout@gmail.com
License: MIT license
Keywords: nurgle
Platform: UNKNOWN
Classifier: Development Status :: 2 - Pre-Alpha
Classifier: Intended Audience :: Developers
Classifier: License :: OSI Approved :: MIT License
Classifier: Natural Language :: English
Classifier: Programming Language :: Python :: 3
Classifier: Programming Language :: Python :: 3.5
Classifier: Programming Language :: Python :: 3.6
Classifier: Programming Language :: Python :: 3.7
Classifier: Programming Language :: Python :: 3.8
Requires-Python: >=3.5
